odoo/addons/l10n_it_website_sale_fatturapa/README.rst
odoo/addons/l10n_it_website_sale_fatturapa/__init__.py
odoo/addons/l10n_it_website_sale_fatturapa/__manifest__.py
odoo/addons/l10n_it_website_sale_fatturapa/controllers/__init__.py
odoo/addons/l10n_it_website_sale_fatturapa/controllers/main.py
odoo/addons/l10n_it_website_sale_fatturapa/i18n/it.po
odoo/addons/l10n_it_website_sale_fatturapa/i18n/l10n_it_website_sale_fatturapa.pot
odoo/addons/l10n_it_website_sale_fatturapa/readme/DESCRIPTION.rst
odoo/addons/l10n_it_website_sale_fatturapa/static/description/icon.png
odoo/addons/l10n_it_website_sale_fatturapa/static/description/index.html
odoo/addons/l10n_it_website_sale_fatturapa/static/src/js/l10n_it_website_sale_fatturapa.js
odoo/addons/l10n_it_website_sale_fatturapa/views/templates.xml
odoo14_addon_l10n_it_website_sale_fatturapa-14.0.1.0.1.dev3.dist-info/METADATA
odoo14_addon_l10n_it_website_sale_fatturapa-14.0.1.0.1.dev3.dist-info/WHEEL
odoo14_addon_l10n_it_website_sale_fatturapa-14.0.1.0.1.dev3.dist-info/top_level.txt
odoo14_addon_l10n_it_website_sale_fatturapa-14.0.1.0.1.dev3.dist-info/RECORD
