Metadata-Version: 2.1
Name: odoo14-addon-l10n-it-website-sale-fatturapa
Version: 14.0.1.0.1.dev3
Summary: Aggiunge i campi necessari alla fatturazione elettronica nel form del checkout
Home-page: https://github.com/OCA/l10n-italy/tree/14.0/l10n_it_website_sale_fatturapa
Author: Odoo Community Association (OCA)
Author-email: support@odoo-community.org
License: AGPL-3
Platform: UNKNOWN
Classifier: Programming Language :: Python
Classifier: Framework :: Odoo
Classifier: Framework :: Odoo :: 14.0
Classifier: License :: OSI Approved :: GNU Affero General Public License v3
Requires-Python: >=3.6
Requires-Dist: odoo14-addon-l10n-it-fatturapa
Requires-Dist: odoo14-addon-l10n-it-website-sale-fiscalcode
Requires-Dist: odoo <14.1dev,>=14.0a
